Workbook
Name aporte_mensal: Calculadora!$D$12
Name dy_mensal: Calculadora!$D$16
Name ganho_acumulado: Calculadora!$D$19
Name patrimonio_acumulado: Calculadora!$D$20
Name renda_mensal: Calculadora!$D$21
Name rendimento_carteira: Calculadora!$D$17
Name salario: Calculadora!$D$10
Name tempo_de_aportes: Calculadora!$D$15
Name total_aporte: Calculadora!$D$18

Sheet Resumo sobre FIIs
A1: O que são Fundos Imobiliários e como funcionam
A3: Para a Comissão de Valores Mobiliários (CVM), os Fundos de Investimento Imobiliário são "comunhões de recursos captados por meio do sistema de distribuição de valores mobiliários e destinados à aplicação em empreendimentos imobiliários".
A4: É como se você e milhares de outras pessoas juntassem dinheiro para comprar imóveis comerciais e dividissem os lucros proporcionalmente.
A5: O funcionamento é simples. Quando você compra cotas de um FII, está adquirindo uma pequena fração de um portfólio imobiliário. É como comprar uma "fatia" de um shopping center ou de um edifício comercial.
A6: A diferença é que, em vez de lidar com contratos de locação, manutenção e inadimplência, você apenas recebe sua parte dos rendimentos mensalmente.
A8: Conheça os tipos de Fundos Imobiliários
A9: Os principais tipos de Fundos Imobiliários são os de tijolo, papel, Fundos de Fundos (FoFs), híbridos, Fiagros e Fundos de desenvolvimento. Confira os detalhes:
A11: FIIs de Tijolo
A13: Os FIIs de tijolo possuem imóveis físicos reais. Shoppings, edifícios comerciais, galpões logísticos, hospitais, hotéis, se você pode tocar, provavelmente existe um FII de tijolo para isso. Estes fundos vivem da receita de aluguéis e, eventualmente, da valorização dos imóveis.
A14: A grande vantagem está na tangibilidade e na previsibilidade da renda. Contratos de locação bem estruturados podem proporcionar fluxo de caixa estável por anos.
A15: Por outro lado, a gestão é mais complexa, os custos operacionais são maiores, e a liquidez dos ativos é menor, afinal, não se vende um shopping center da noite para o dia.
A17: FIIs de Papel
... A91: Vale lembrar que operações de day trade com FIIs (compra e venda no mesmo dia) são tributadas em 20% sobre o ganho, independentemente do valor.

Sheet Calculadora
B9: CONFIGURAÇÕES
B10: Salário | D10: 5000
B11: % de aporte do Salário | D11: 0.1
B12: Aporte mensal | D12: =D10*D11 -> 500
B14: INVESTIMENTO
B15: Tempo Total de Aportes(anos) | D15: 10
B16: Dividend Yield Mensal | D16: 0.0075
B17: Rendimento Mensal Carteira | D17: 0.002
B18: Total Aportado | D18: =aporte_mensal*tempo_de_aportes*12 -> 60000
B19: Ganho Acumulado | D19: =FV((dy_mensal+rendimento_carteira),tempo_de_aportes*12,aporte_mensal*-1)-(aporte_mensal*tempo_de_aportes*12) -> 51052.03
B20: Patrimônio acumulado | D20: =total_aporte + ganho_acumulado -> 111052.03
B21: Renda Mensal após período de aporte | D21: =patrimonio_acumulado*(dy_mensal+rendimento_carteira) -> 1054.9943
B23: CENÁRIOS DE APORTE | C23: PATRIMÔNIO ACUMULADO | D23: RENDA MENSAL
A24: 2 | B24: 2 Anos | C24: =FV(($D$16+$D$17),$A24*12,aporte_mensal*-1,1) -> 13405.812 | D24: =C24*($D$17+$D$16) -> 127.35521
A25: 5 | B25: 5 Anos | C25: =FV(($D$16+$D$17),$A25*12,aporte_mensal*-1,1) -> 40183.288 | D25: =C25*($D$17+$D$16) -> 381.74123
A26: 10 | B26: 10 Anos | C26: =FV(($D$16+$D$17),$A26*12,aporte_mensal*-1,1) -> 111048.92 | D26: =C26*($D$17+$D$16) -> 1054.9647
A27: 20 | B27: 20 Anos | C27: =FV(($D$16+$D$17),$A27*12,aporte_mensal*-1,1) -> 456412.9 | D27: =C27*($D$17+$D$16) -> 4335.9226
A28: 30 | B28: 30 Anos | C28: =FV(($D$16+$D$17),$A28*12,aporte_mensal*-1,1) -> 1530490.9 | D28: =C28*($D$17+$D$16) -> 14539.664
B30: PERFIL | D30: Conservador | F30: Altere seu perfil aqui
B31: APORTE MENSAL | D31: =aporte_mensal -> 500
B33: TIPO DE FII | C33: PERCENTUAL SUGERIDO | D33: VALORES
B34: PAPEL | C34: =VLOOKUP($D$30&"-"&B34,PROCV!$A:$D,4,FALSE) -> 0.45 | D34: =D31*$C$34 -> 225
B35: TIJOLO | C35: =VLOOKUP($D$30&"-"&B35,PROCV!$A:$D,4,FALSE) -> 0.3 | D35: =C35*$D$31 -> 150
B36: HÍBRIDOS | C36: =VLOOKUP($D$30&"-"&B36,PROCV!$A:$D,4,FALSE) -> 0.05 | D36: =C36*$D$31 -> 25
B37: FOFs | C37: =VLOOKUP($D$30&"-"&B37,PROCV!$A:$D,4,FALSE) -> 0.1 | D37: =C37*$D$31 -> 50
B38: DESENVOLVIMENTO | C38: =VLOOKUP($D$30&"-"&B38,PROCV!$A:$D,4,FALSE) -> 0.05 | D38: =C38*$D$31 -> 25
B39: FIAGRO | C39: =VLOOKUP($D$30&"-"&B39,PROCV!$A:$D,4,FALSE) -> 0.05 | D39: =C39*$D$31 -> 25

Sheet Resumo da Calculadora
A1: O patrimônio acumulado não considera impostos, taxas nem variações nas taxas, também não considera corretagens e pressupõe que os retornos sejam constantes e reinvestidos mensalmente.
A2: O cálculo pressupõe que o primeiro aporte foi feito no início do primeiro mês para que já tenha rendimento e dividendos pagos.
A3: O cálculo da renda mensal é o somatório dos aportes mensais(Aporte Mensal e reinvestimento dos dividendos) e Rendimento Mensal da Carteira.
A4: Há uma diferença importante entre resgatar um percentual ao mês e receber um percentual ao mês sem reduzir o patrimônio. - Se o investimento continuar rendendo o somatório dos aportes mensais(Aporte Mensal e reinvestimento dos dividendos) e Rendimento Mensal da Carteira ao mês e você retirar exatamente esse percentual sobre o saldo, o patrimônio permanecerá aproximadamente constante, antes de impostos, taxas e oscilações. - Se o rendimento efetivo for inferior ao percentual resgatado, o patrimônio diminuirá. - Se o rendimento superar o resgate, o patrimônio poderá crescer. A renda calculada é, portanto, uma estimativa bruta inicial, não uma garantia de rendimento. A sustentabilidade depende de o investimento realmente entregar essa taxa líquida de custos e tributos.
A5: As linhas com fundo cinza são resultados dos dados inseridos nas linhas de fundo branco.
A6: O rendimento mensal da carteira leva em conta a evolução de rendimento do IFIX, que é o índice que mede o desempenho médio dos principais Fundos de Investimento Imobiliário (FIIs) listados na B3. Criado em 2012, o indicador reflete a variação dos preços e os rendimentos distribuídos pelos fundos que compõem sua carteira teórica.O IFIX reflete não só a valorização das cotas, mas também os rendimentos distribuídos como dividendos e juros sobre capital próprio. É um índice de retorno total, ou seja, considera tanto a oscilação dos preços quanto os proventos pagos. O seu retorno nos últimos 10 anos foi de cerca de 115%, por isso, não coloque valores muito fora do contexto real nas células Rendimento Mensal Carteira e Dividend Yield

Sheet PROCV
A2: CHAVE | B2: PERFIL | C2: TIPO DE FII | D2: %
A3: =B3&"-"&C3 -> Conservador-PAPEL | B3: Conservador | C3: PAPEL | D3: 0.45
A4: =B4&"-"&C4 -> Conservador-TIJOLO | B4: Conservador | C4: TIJOLO | D4: 0.3
A5: =B5&"-"&C5 -> Conservador-HÍBRIDOS | B5: Conservador | C5: HÍBRIDOS | D5: 0.05 | H5: %
A6: =B6&"-"&C6 -> Conservador-FOFs | B6: Conservador | C6: FOFs | D6: 0.1 | F6: Moderado-TIJOLO | H6: =VLOOKUP(F6,$A1:$D20,4,FALSE) -> 0.3
A7: =B7&"-"&C7 -> Conservador-DESENVOLVIMENTO | B7: Conservador | C7: DESENVOLVIMENTO | D7: 0.05
A8: =B8&"-"&C8 -> Conservador-FIAGRO | B8: Conservador | C8: FIAGRO | D8: 0.05
A9: =B9&"-"&C9 -> Moderado-PAPEL | B9: Moderado | C9: PAPEL | D9: 0.3
A10: =B10&"-"&C10 -> Moderado-TIJOLO | B10: Moderado | C10: TIJOLO | D10: 0.3
A11: =B11&"-"&C11 -> Moderado-HÍBRIDOS | B11: Moderado | C11: HÍBRIDOS | D11: 0.1
A12: =B12&"-"&C12 -> Moderado-FOFs | B12: Moderado | C12: FOFs | D12: 0.1
A13: =B13&"-"&C13 -> Moderado-DESENVOLVIMENTO | B13: Moderado | C13: DESENVOLVIMENTO | D13: 0.1
A14: =B14&"-"&C14 -> Moderado-FIAGRO | B14: Moderado | C14: FIAGRO | D14: 0.1
A15: =B15&"-"&C15 -> Agressivo-PAPEL | B15: Agressivo | C15: PAPEL | D15: 0.2
A16: =B16&"-"&C16 -> Agressivo-TIJOLO | B16: Agressivo | C16: TIJOLO | D16: 0.2
A17: =B17&"-"&C17 -> Agressivo-HÍBRIDOS | B17: Agressivo | C17: HÍBRIDOS | D17: 0.15
A18: =B18&"-"&C18 -> Agressivo-FOFs | B18: Agressivo | C18: FOFs | D18: 0.15
... A20: =B20&"-"&C20 -> Agressivo-FIAGRO | B20: Agressivo | C20: FIAGRO | D20: 0.15
